src/__init__.py
src/gptizer.py
src/main.py
src/models.py
src/output_builder.py
src/settings.py
gptize-0.5.1.dist-info/LICENSE
gptize-0.5.1.dist-info/METADATA
gptize-0.5.1.dist-info/WHEEL
gptize-0.5.1.dist-info/entry_points.txt
gptize-0.5.1.dist-info/top_level.txt
gptize-0.5.1.dist-info/RECORD
