Metadata-Version: 2.1
Name: gptize
Version: 0.5.1
Summary: Gptize is a tool designed to concatenate the contents of project files for ChatGPT
Home-page: https://github.com/aabee-tech/gptize
Author: SvetlovTech
Author-email: svetlovtech@aabee.tech
License: UNKNOWN
Platform: UNKNOWN
Classifier: Programming Language :: Python :: 3
Classifier: License :: OSI Approved :: MIT License
Classifier: Operating System :: OS Independent
Requires-Python: >=3.9.0
License-File: LICENSE
Requires-Dist: pathspec==0.11.2
Requires-Dist: pyperclip==1.9.0
Requires-Dist: tiktoken==0.8.0
